sr/robot3/__init__.py
sr/robot3/_version.py
sr/robot3/arduino.py
sr/robot3/astoria.py
sr/robot3/camera.py
sr/robot3/exceptions.py
sr/robot3/game_specific.py
sr/robot3/kch.py
sr/robot3/logging.py
sr/robot3/marker.py
sr/robot3/motor_board.py
sr/robot3/mqtt.py
sr/robot3/power_board.py
sr/robot3/py.typed
sr/robot3/raw_serial.py
sr/robot3/robot.py
sr/robot3/serial_wrapper.py
sr/robot3/servo_board.py
sr/robot3/timeout.py
sr/robot3/utils.py
sr/robot3/calibrations/__init__.py
sr/robot3/simulator/__init__.py
sr/robot3/simulator/camera.py
sr/robot3/simulator/time_server.py
sr_robot3-2026.0.2.dist-info/licenses/LICENSE
sr_robot3-2026.0.2.dist-info/METADATA
sr_robot3-2026.0.2.dist-info/WHEEL
sr_robot3-2026.0.2.dist-info/top_level.txt
sr_robot3-2026.0.2.dist-info/RECORD
