Metadata-Version: 2.4
Name: sr-robot3
Version: 2026.0.2
Summary: Student Robotics API for Python 3
Author-email: Student Robotics <kit-team@studentrobotics.org>
License: MIT License
Project-URL: Repository, https://github.com/srobo/sr-robot
Project-URL: Homepage, https://studentrobotics.org
Project-URL: Documentation, https://docs.studentrobotics.org
Classifier: Topic :: Software Development :: Libraries :: Python Modules
Classifier: Operating System :: OS Independent
Classifier: Development Status :: 5 - Production/Stable
Classifier: Typing :: Typed
Classifier: Topic :: Education
Requires-Python: >=3.9
License-File: LICENSE
Requires-Dist: pyserial<4,>=3
Requires-Dist: april_vision==3.0.0
Requires-Dist: paho-mqtt<3,>=2
Requires-Dist: pydantic<2,>=1.9.1
Requires-Dist: typing-extensions; python_version < "3.10"
Requires-Dist: tomli<3,>=2.0.1; python_version < "3.11"
Provides-Extra: dev
Requires-Dist: flake8; extra == "dev"
Requires-Dist: isort; extra == "dev"
Requires-Dist: mypy<2,>=1.7; extra == "dev"
Requires-Dist: build; extra == "dev"
Requires-Dist: types-pyserial; extra == "dev"
Requires-Dist: pytest; extra == "dev"
Requires-Dist: pytest-cov; extra == "dev"
Requires-Dist: paho-mqtt<3,>=2; extra == "dev"
Provides-Extra: vision
Requires-Dist: opencv-python-headless<5,>=4.10; extra == "vision"
Dynamic: license-file
